{
	"parent": "adv_help:kill_all_mobs/zombified_piglin",
	"display": {
		"icon": {
			"item": "minecraft:zoglin_spawn_egg"
		},
		"title": "怪物狩猎：僵尸疣猪兽",
		"description": "杀死一只僵尸疣猪兽",
		"frame": "goal",
		"show_toast": true,
		"announce_to_chat": true,
		"hidden": false
	},
	"criteria": {
		"zoglin": {
			"trigger": "minecraft:player_killed_entity",
			"conditions": {
				"entity": [
					{
						"condition": "minecraft:entity_properties",
						"predicate": {
							"type": "minecraft:zoglin"
						},
						"entity": "this"
					}
				]
			}
		}
	},
	"requirements": [
		[
			"zoglin"
		]
	]
}